bellcoin_yespower.cp35-win32.pyd
bellcoin_yespower-1.0.6.dist-info/METADATA
bellcoin_yespower-1.0.6.dist-info/RECORD
bellcoin_yespower-1.0.6.dist-info/WHEEL
bellcoin_yespower-1.0.6.dist-info/top_level.txt
