Metadata-Version: 2.1
Name: bellcoin-yespower
Version: 1.0.6
Summary: Bindings for yespower-1.0 proof of work used by bellcoin
Home-page: https://github.com/streetcrypto7/bellcoin_yespower_python
Author: streetcrypto7
Author-email: streetcrypto7@protonmail.com
License: UNKNOWN
Platform: UNKNOWN
